zdb/__init__.py
zdb/drawing/__init__.py
zdb/drawing/draw_data_mc.py
zdb/drawing/draw_variation.py
zdb/drawing/generate_html.py
zdb/modules/__init__.py
zdb/modules/analyse.py
zdb/modules/df_process.py
zdb/modules/df_skim.py
zdb/modules/df_slim.py
zdb/modules/draw.py
zdb/modules/multirun.py
zdb/modules/skim.py
zdb/scripts/__init__.py
zdb/scripts/draw.py
zdb/scripts/draw_data_mc.py
zdb/scripts/draw_variation.py
zdb/scripts/zdb_analyse.py
zdb/scripts/zdb_resume.py
zdb/scripts/zdb_skim.py
zdb/scripts/zdb_slim.py
zdb_analysis-0.1.7.data/scripts/zdb_analyse.py
zdb_analysis-0.1.7.data/scripts/zdb_resume.py
zdb_analysis-0.1.7.data/scripts/zdb_skim.py
zdb_analysis-0.1.7.dist-info/LICENSE
zdb_analysis-0.1.7.dist-info/METADATA
zdb_analysis-0.1.7.dist-info/WHEEL
zdb_analysis-0.1.7.dist-info/top_level.txt
zdb_analysis-0.1.7.dist-info/RECORD
